LICENSE
pisql/__init__.py
pisql/cli/__init__.py
pisql/cli/config.py
pisql/cli/execute.py
pisql/cli/run.py
pisql/core/__init__.py
pisql/core/generate.py
pisql/core/isql.py
pisql/core/isql_config.py
pisql/main.py
pisql/utils/__init__.py
pisql/utils/local_store.py
pisql/utils/paths.py
pisql/utils/render.py
README.md
pisql-0.1.32.dist-info/entry_points.txt
pisql-0.1.32.dist-info/LICENSE
pisql-0.1.32.dist-info/METADATA
pisql-0.1.32.dist-info/WHEEL
pisql-0.1.32.dist-info/RECORD
