Metadata-Version: 2.1
Name: pisql
Version: 0.1.32
Summary: pisql is a CLI + lightweight python library to interact with a Sybase ASE database.
License: LICENSE
Author: Arno V
Author-email: arno@veletanlic.org
Requires-Python: >=3.8,<4.0
Classifier: License :: Other/Proprietary License
Classifier: Programming Language :: Python :: 3
Classifier: Programming Language :: Python :: 3.8
Classifier: Programming Language :: Python :: 3.9
Classifier: Programming Language :: Python :: 3.10
Classifier: Programming Language :: Python :: 3.11
Requires-Dist: iotree (==0.1.21-post1)
Requires-Dist: polars (>=0.15.13,<0.16.0)
Requires-Dist: typer[all] (>=0.7.0,<0.8.0)
